MANIFEST.in
README
esetup.py
freeze.py
makedist
setup.cfg
setup.py
PEATDB/Actions.py
PEATDB/Ancestry.py
PEATDB/App.icns
PEATDB/App.ico
PEATDB/Base.py
PEATDB/BusyBar.py
PEATDB/Compare.py
PEATDB/DNA_sequence.py
PEATDB/Dialogs.py
PEATDB/DictEdit.py
PEATDB/Extfile.py
PEATDB/File_images.py
PEATDB/Filtering.py
PEATDB/GUI_helper.py
PEATDB/IO.py
PEATDB/Labbook.py
PEATDB/Meta.py
PEATDB/Mutate.py
PEATDB/Optparse.py
PEATDB/PE.py
PEATDB/PEATApp.py
PEATDB/PEATTables.py
PEATDB/PEAT_images.py
PEATDB/PILView.py
PEATDB/Parsers.py
PEATDB/Plugins.py
PEATDB/Prefs.py
PEATDB/ProgressBar.py
PEATDB/PylabPlot.py
PEATDB/Record.py
PEATDB/Sandbox.py
PEATDB/Search.py
PEATDB/Sequence.py
PEATDB/TableFormula.py
PEATDB/TableModels.py
PEATDB/TablePlot.py
PEATDB/Table_images.py
PEATDB/Tables.py
PEATDB/Tables_IO.py
PEATDB/Utils.py
PEATDB/Yasara.py
PEATDB/__init__.py
PEATDB/license.txt
PEATDB/markup.py
PEATDB/sequence_alignment.py
PEATDB/textFrame.py
PEATDB/tooltip.py
PEATDB/web.py
PEATDB/zeo.conf
PEATDB/zeo.init
PEATDB/zodbtest.py
PEATDB.egg-info/PKG-INFO
PEATDB.egg-info/SOURCES.txt
PEATDB.egg-info/dependency_links.txt
PEATDB.egg-info/entry_points.txt
PEATDB.egg-info/requires.txt
PEATDB.egg-info/top_level.txt
PEATDB/DNAtool/DNA_Edit.py
PEATDB/DNAtool/DNA_sequencing.py
PEATDB/DNAtool/DNAseq.seq
PEATDB/DNAtool/DNAtool.ico
PEATDB/DNAtool/DNAtool.py
PEATDB/DNAtool/DNAtool_IO.py
PEATDB/DNAtool/DNAtool_mac.icns
PEATDB/DNAtool/DataBase_GUI.py
PEATDB/DNAtool/Main.py
PEATDB/DNAtool/ORF_module.py
PEATDB/DNAtool/PDBDumper.py
PEATDB/DNAtool/Restriction_Digest_driver.py
PEATDB/DNAtool/__init__.py
PEATDB/DNAtool/enzyme.dat
PEATDB/DNAtool/evaluate_primer.py
PEATDB/DNAtool/mutation.py
PEATDB/DNAtool/primer_alignment.py
PEATDB/DNAtool/primer_database.py
PEATDB/DNAtool/primer_design_GUI.py
PEATDB/DNAtool/restriction_enzymes.DAT
PEATDB/DNAtool/seq_utils.py
PEATDB/DNAtool/test.DTP
PEATDB/Ekin/2lzt.pdb
PEATDB/Ekin/Base.py
PEATDB/Ekin/Convert.py
PEATDB/Ekin/Dataset.py
PEATDB/Ekin/Ekin.ico
PEATDB/Ekin/Ekin_CD.py
PEATDB/Ekin/Ekin_images.py
PEATDB/Ekin/Ekin_main.py
PEATDB/Ekin/Ekin_map.py
PEATDB/Ekin/Ekin_prefs.py
PEATDB/Ekin/ExpConditions.py
PEATDB/Ekin/Fitter_scipy.py
PEATDB/Ekin/Fitting.py
