Metadata-Version: 1.0
Name: PEATDB
Version: 2.3
Summary: Protein Engineering Analysis Tool
Home-page: http://enzyme.ucd.ie/PEAT
Author: Nielsen Group, UCD
Author-email: farrell.damien[at]gmail.com
License: GPL v3
Platform: UNKNOWN
